{
    "/js/app.js": "/js/app.js",
    "/js/app.6ebf99729350e3e4a1c2.hot-update.js": "/js/app.6ebf99729350e3e4a1c2.hot-update.js",
    "/js/app.0df1036fc8499230c528.hot-update.js": "/js/app.0df1036fc8499230c528.hot-update.js",
    "/js/app.74398c0e9f5e013673d6.hot-update.js": "/js/app.74398c0e9f5e013673d6.hot-update.js",
    "/js/app.cdf4c9fa6c9251ac0d21.hot-update.js": "/js/app.cdf4c9fa6c9251ac0d21.hot-update.js",
    "/js/app.e5338dc9f8aea26b5fd6.hot-update.js": "/js/app.e5338dc9f8aea26b5fd6.hot-update.js",
    "/js/app.ec41267b8be6ec3daa6e.hot-update.js": "/js/app.ec41267b8be6ec3daa6e.hot-update.js",
    "/js/app.bd472df883fac225baa9.hot-update.js": "/js/app.bd472df883fac225baa9.hot-update.js",
    "/js/app.56c47cb70ba4f8c72f4a.hot-update.js": "/js/app.56c47cb70ba4f8c72f4a.hot-update.js",
    "/js/app.a0b5f7ca6817afd0d97a.hot-update.js": "/js/app.a0b5f7ca6817afd0d97a.hot-update.js",
    "/js/app.0b84882fe7be86894c43.hot-update.js": "/js/app.0b84882fe7be86894c43.hot-update.js",
    "/js/app.3a8603374dac100ba07e.hot-update.js": "/js/app.3a8603374dac100ba07e.hot-update.js",
    "/js/app.ba6bf3271f2be0ab42f5.hot-update.js": "/js/app.ba6bf3271f2be0ab42f5.hot-update.js",
    "/js/app.99d420bb0f4514aaefcf.hot-update.js": "/js/app.99d420bb0f4514aaefcf.hot-update.js",
    "/js/app.29a20fb9cb8e2b94826a.hot-update.js": "/js/app.29a20fb9cb8e2b94826a.hot-update.js",
    "/js/app.e800a763d4e55c010a49.hot-update.js": "/js/app.e800a763d4e55c010a49.hot-update.js",
    "/js/app.93acaf5cdfcfa9d0f9cf.hot-update.js": "/js/app.93acaf5cdfcfa9d0f9cf.hot-update.js",
    "/js/app.f912e40b20edde0b1319.hot-update.js": "/js/app.f912e40b20edde0b1319.hot-update.js",
    "/js/app.5cac8730a0bb3a6b02a8.hot-update.js": "/js/app.5cac8730a0bb3a6b02a8.hot-update.js",
    "/js/app.5d66ac66c14b010584be.hot-update.js": "/js/app.5d66ac66c14b010584be.hot-update.js",
    "/js/app.d8b2b9e222a80bc5b278.hot-update.js": "/js/app.d8b2b9e222a80bc5b278.hot-update.js",
    "/js/app.61fee1fad4058f21cf92.hot-update.js": "/js/app.61fee1fad4058f21cf92.hot-update.js",
    "/js/app.da44eea186d6ccb3b6a8.hot-update.js": "/js/app.da44eea186d6ccb3b6a8.hot-update.js",
    "/js/app.88fba956a26c51a756d6.hot-update.js": "/js/app.88fba956a26c51a756d6.hot-update.js",
    "/js/app.e81d585cb01ef16cd889.hot-update.js": "/js/app.e81d585cb01ef16cd889.hot-update.js",
    "/js/app.9f79a64668b931f0bf37.hot-update.js": "/js/app.9f79a64668b931f0bf37.hot-update.js",
    "/js/app.4bcbb372be8e98dda9a7.hot-update.js": "/js/app.4bcbb372be8e98dda9a7.hot-update.js",
    "/js/app.ff5bae678cef4b761394.hot-update.js": "/js/app.ff5bae678cef4b761394.hot-update.js",
    "/js/app.170211e26a6b3857a0bd.hot-update.js": "/js/app.170211e26a6b3857a0bd.hot-update.js",
    "/js/app.f90abc09b67bd7227033.hot-update.js": "/js/app.f90abc09b67bd7227033.hot-update.js",
    "/js/app.92f8dd03b264093b42e3.hot-update.js": "/js/app.92f8dd03b264093b42e3.hot-update.js",
    "/js/app.dae9d64450863780c1fd.hot-update.js": "/js/app.dae9d64450863780c1fd.hot-update.js",
    "/js/app.fd1424fb5edb7f7d78e0.hot-update.js": "/js/app.fd1424fb5edb7f7d78e0.hot-update.js",
    "/js/app.1d8962f8ed59aad66200.hot-update.js": "/js/app.1d8962f8ed59aad66200.hot-update.js",
    "/js/app.94bd2a9bf92ed4b287c3.hot-update.js": "/js/app.94bd2a9bf92ed4b287c3.hot-update.js",
    "/js/app.792b9a86d3ac6be3a6ca.hot-update.js": "/js/app.792b9a86d3ac6be3a6ca.hot-update.js",
    "/js/app.eca99b56041f663196be.hot-update.js": "/js/app.eca99b56041f663196be.hot-update.js",
    "/js/app.cf2e55abb46c0193e19c.hot-update.js": "/js/app.cf2e55abb46c0193e19c.hot-update.js",
    "/js/app.3ae898d5bb8470ce9175.hot-update.js": "/js/app.3ae898d5bb8470ce9175.hot-update.js",
    "/js/app.cb8d9da7d39cd4db8021.hot-update.js": "/js/app.cb8d9da7d39cd4db8021.hot-update.js",
    "/js/app.a73578c6167a2b561d1b.hot-update.js": "/js/app.a73578c6167a2b561d1b.hot-update.js",
    "/js/app.5ea6dfcf7f9d18ce9def.hot-update.js": "/js/app.5ea6dfcf7f9d18ce9def.hot-update.js",
    "/js/app.6db82ebe0df060e4e85f.hot-update.js": "/js/app.6db82ebe0df060e4e85f.hot-update.js",
    "/js/app.58b05869212bd57a3f66.hot-update.js": "/js/app.58b05869212bd57a3f66.hot-update.js",
    "/js/app.95931396e70ec6af8fa8.hot-update.js": "/js/app.95931396e70ec6af8fa8.hot-update.js",
    "/js/app.f40e082115f826d1a7f7.hot-update.js": "/js/app.f40e082115f826d1a7f7.hot-update.js",
    "/js/app.7f96f39cac98a238b5d9.hot-update.js": "/js/app.7f96f39cac98a238b5d9.hot-update.js",
    "/js/app.cda3e40e5a114b6dd95e.hot-update.js": "/js/app.cda3e40e5a114b6dd95e.hot-update.js",
    "/js/app.8a4a77f38efb1e9c0ab5.hot-update.js": "/js/app.8a4a77f38efb1e9c0ab5.hot-update.js",
    "/js/app.275252ef25f477b7eae1.hot-update.js": "/js/app.275252ef25f477b7eae1.hot-update.js",
    "/js/app.99c9ce3ab85454606026.hot-update.js": "/js/app.99c9ce3ab85454606026.hot-update.js",
    "/js/app.6775b0ab0d0015e76cf6.hot-update.js": "/js/app.6775b0ab0d0015e76cf6.hot-update.js",
    "/js/app.a5ccef6e5db44b006dbe.hot-update.js": "/js/app.a5ccef6e5db44b006dbe.hot-update.js",
    "/js/app.2a5fd9b0aa145bfbb01f.hot-update.js": "/js/app.2a5fd9b0aa145bfbb01f.hot-update.js",
    "/js/app.31668b11684f60e6d434.hot-update.js": "/js/app.31668b11684f60e6d434.hot-update.js",
    "/js/app.75e886f458a944743257.hot-update.js": "/js/app.75e886f458a944743257.hot-update.js",
    "/js/app.f84d21614884dc06c33e.hot-update.js": "/js/app.f84d21614884dc06c33e.hot-update.js",
    "/js/app.1b4c64f6b379e82dbb02.hot-update.js": "/js/app.1b4c64f6b379e82dbb02.hot-update.js",
    "/js/app.1c91bbbec5173c389775.hot-update.js": "/js/app.1c91bbbec5173c389775.hot-update.js",
    "/js/app.190fa9ec9ccc44ca4d98.hot-update.js": "/js/app.190fa9ec9ccc44ca4d98.hot-update.js",
    "/js/app.9bd7ef9fcdb7a6ee0c19.hot-update.js": "/js/app.9bd7ef9fcdb7a6ee0c19.hot-update.js",
    "/js/app.fd7f4d469d72c24e348d.hot-update.js": "/js/app.fd7f4d469d72c24e348d.hot-update.js",
    "/js/app.c719b469731fbb67f7d4.hot-update.js": "/js/app.c719b469731fbb67f7d4.hot-update.js",
    "/js/app.ca0e962167bd21412de6.hot-update.js": "/js/app.ca0e962167bd21412de6.hot-update.js",
    "/js/app.3fdb71b2d3039c781b2d.hot-update.js": "/js/app.3fdb71b2d3039c781b2d.hot-update.js",
    "/js/app.ff0fc8d5a9951357c2fc.hot-update.js": "/js/app.ff0fc8d5a9951357c2fc.hot-update.js",
    "/js/app.d8906b054908da85bdbf.hot-update.js": "/js/app.d8906b054908da85bdbf.hot-update.js",
    "/js/app.db9df64b5c7f95dc9715.hot-update.js": "/js/app.db9df64b5c7f95dc9715.hot-update.js",
    "/js/app.7c17f7f664ce116ca715.hot-update.js": "/js/app.7c17f7f664ce116ca715.hot-update.js",
    "/js/app.66f527a3980d27418e29.hot-update.js": "/js/app.66f527a3980d27418e29.hot-update.js",
    "/js/app.212df57b02a471182da0.hot-update.js": "/js/app.212df57b02a471182da0.hot-update.js",
    "/js/app.d66a12a79703654ee460.hot-update.js": "/js/app.d66a12a79703654ee460.hot-update.js",
    "/js/app.13f46c079734ff3ee949.hot-update.js": "/js/app.13f46c079734ff3ee949.hot-update.js",
    "/js/app.7a537555eca71e15e190.hot-update.js": "/js/app.7a537555eca71e15e190.hot-update.js",
    "/js/app.1503448874729b0e22e7.hot-update.js": "/js/app.1503448874729b0e22e7.hot-update.js",
    "/js/app.f40704744c8c37d46aec.hot-update.js": "/js/app.f40704744c8c37d46aec.hot-update.js",
    "/js/app.ed9df76422972aeb3f57.hot-update.js": "/js/app.ed9df76422972aeb3f57.hot-update.js",
    "/js/app.525bce7b9c8b0aaaf365.hot-update.js": "/js/app.525bce7b9c8b0aaaf365.hot-update.js",
    "/js/app.7070521bdee5d12c7e1f.hot-update.js": "/js/app.7070521bdee5d12c7e1f.hot-update.js",
    "/js/app.b5b03fe42860958b439e.hot-update.js": "/js/app.b5b03fe42860958b439e.hot-update.js",
    "/js/app.7d4ec83c608870046d1d.hot-update.js": "/js/app.7d4ec83c608870046d1d.hot-update.js",
    "/js/app.cdd488f9197a5bae0fd8.hot-update.js": "/js/app.cdd488f9197a5bae0fd8.hot-update.js",
    "/js/app.b87b676001af61766050.hot-update.js": "/js/app.b87b676001af61766050.hot-update.js",
    "/js/app.c1179b571f6b7f2cf698.hot-update.js": "/js/app.c1179b571f6b7f2cf698.hot-update.js",
    "/js/app.6df68d322df9175686c4.hot-update.js": "/js/app.6df68d322df9175686c4.hot-update.js",
    "/js/app.bf783c439110899a747d.hot-update.js": "/js/app.bf783c439110899a747d.hot-update.js",
    "/js/app.110cd3e913f9e575f2b9.hot-update.js": "/js/app.110cd3e913f9e575f2b9.hot-update.js",
    "/js/app.41d49cf162fb412541aa.hot-update.js": "/js/app.41d49cf162fb412541aa.hot-update.js",
    "/js/app.0dd57fa9ab939d975b0a.hot-update.js": "/js/app.0dd57fa9ab939d975b0a.hot-update.js",
    "/js/app.267deb64516d63d2289d.hot-update.js": "/js/app.267deb64516d63d2289d.hot-update.js",
    "/js/app.d56444753147223cb024.hot-update.js": "/js/app.d56444753147223cb024.hot-update.js",
    "/js/app.dd5074d429c6a0709b43.hot-update.js": "/js/app.dd5074d429c6a0709b43.hot-update.js",
    "/js/app.7fd7a6c337a6d77d9627.hot-update.js": "/js/app.7fd7a6c337a6d77d9627.hot-update.js",
    "/js/app.b253f5e99e0ba6c3933e.hot-update.js": "/js/app.b253f5e99e0ba6c3933e.hot-update.js",
    "/js/app.ed2febf86d5b8c44ca3d.hot-update.js": "/js/app.ed2febf86d5b8c44ca3d.hot-update.js",
    "/js/app.b4cfb43163c63979c49e.hot-update.js": "/js/app.b4cfb43163c63979c49e.hot-update.js",
    "/js/app.75320241f1b5d52afa33.hot-update.js": "/js/app.75320241f1b5d52afa33.hot-update.js",
    "/js/app.ea1320ece065caae70e5.hot-update.js": "/js/app.ea1320ece065caae70e5.hot-update.js",
    "/js/app.a181ac83a250979d9f09.hot-update.js": "/js/app.a181ac83a250979d9f09.hot-update.js"
}
